writegithubstat/__init__.py
writegithubstat/githubstat.py
writegithubstat/py.typed
write_githubstat-0.2.1.dist-info/LICENSE
write_githubstat-0.2.1.dist-info/METADATA
write_githubstat-0.2.1.dist-info/WHEEL
write_githubstat-0.2.1.dist-info/RECORD
