Metadata-Version: 2.1
Name: write-githubstat
Version: 0.2.1
Summary: write-githubstat makes it easy to collect, filter and save github statistics to csv files.
License: Apache 2.0
Author: David Vegh
Author-email: david.andras.vegh+github@gmail.com
Requires-Python: >=3.9
Classifier: License :: Other/Proprietary License
Classifier: Programming Language :: Python :: 3
Classifier: Programming Language :: Python :: 3.9
Classifier: Programming Language :: Python :: 3.10
Classifier: Programming Language :: Python :: 3.11
Classifier: Programming Language :: Python :: 3.12
Requires-Dist: pandas (>=2.2.2,<3.0.0)
Requires-Dist: requests (>=2.0.0,<3.0.0)
Project-URL: documentation, https://github.com/veghdev/write-githubstat
Project-URL: homepage, https://github.com/veghdev/write-githubstat
Project-URL: repository, https://github.com/veghdev/write-githubstat
